osparc/__init__.py
osparc/_api_client.py
osparc/_exceptions.py
osparc/_files_api.py
osparc/_http_client.py
osparc/_info.py
osparc/_settings.py
osparc/_solvers_api.py
osparc/_studies_api.py
osparc/_utils.py
osparc/api.py
osparc/data/openapi.json
osparc-0.8.3.dist-info/METADATA
osparc-0.8.3.dist-info/WHEEL
osparc-0.8.3.dist-info/top_level.txt
osparc-0.8.3.dist-info/RECORD
