Metadata-Version: 2.1
Name: osparc
Version: 0.8.3
Summary: osparc.io web API
Home-page: https://itisfoundation.github.io/osparc-simcore-clients/
Author: pcrespov, bisgaard-itis
Author-email: support@osparc.io
License: MIT
Classifier: Development Status :: 3 - Alpha
Classifier: License :: OSI Approved :: MIT License
Classifier: Natural Language :: English
Classifier: Operating System :: OS Independent
Classifier: Programming Language :: Python :: 3
Requires-Dist: httpx
Requires-Dist: nest-asyncio
Requires-Dist: packaging
Requires-Dist: pydantic-settings
Requires-Dist: pydantic
Requires-Dist: tenacity
Requires-Dist: tqdm >=4.48.0
Requires-Dist: osparc-client ==0.8.3
